odoo9_addon_website_forum_censored-9.0.1.0.0-py2.7-nspkg.pth
odoo9_addon_website_forum_censored-9.0.1.0.0.dist-info/top_level.txt
odoo9_addon_website_forum_censored-9.0.1.0.0.dist-info/WHEEL
odoo9_addon_website_forum_censored-9.0.1.0.0.dist-info/RECORD
odoo9_addon_website_forum_censored-9.0.1.0.0.dist-info/metadata.json
odoo9_addon_website_forum_censored-9.0.1.0.0.dist-info/DESCRIPTION.rst
odoo9_addon_website_forum_censored-9.0.1.0.0.dist-info/METADATA
odoo9_addon_website_forum_censored-9.0.1.0.0.dist-info/namespace_packages.txt
odoo_addons/website_forum_censored/__openerp__.py
odoo_addons/website_forum_censored/menuitems.xml
odoo_addons/website_forum_censored/__init__.py
odoo_addons/website_forum_censored/README.rst
odoo_addons/website_forum_censored/security/ir.model.access.csv
odoo_addons/website_forum_censored/models/forum_tag.py
odoo_addons/website_forum_censored/models/forum_post.py
odoo_addons/website_forum_censored/models/__init__.py
odoo_addons/website_forum_censored/models/forum_censored_phrase.py
odoo_addons/website_forum_censored/views/forum_censored_phrase.xml
odoo_addons/website_forum_censored/tests/__init__.py
odoo_addons/website_forum_censored/tests/test_website_forum_censored.py
